MANIFEST.in
README.rst
requirements.txt
setup.py
leaked/__init__.py
leaked/__main__.py
leaked/cli.py
leaked/core.py
leaked/errors.py
leaked/modules.py
leaked/providers.py
leaked/requests.py
leaked.egg-info/PKG-INFO
leaked.egg-info/SOURCES.txt
leaked.egg-info/dependency_links.txt
leaked.egg-info/entry_points.txt
leaked.egg-info/requires.txt
leaked.egg-info/top_level.txt
leaked/modules/freenode.yml
leaked/modules/mutt.yml
leaked/modules/rsa.yml
leaked/modules/wordpress.yml