Metadata-Version: 1.1
Name: leaked
Version: 0.0.3
Summary: Find leaked information in different kind of services
Home-page: https://github.com/timofurrer/leaked
Author: Timo Furrer
Author-email: tuxtimo@gmail.com
License: MIT
Keywords: leaked,credentials,passwords,security,git,github,source,code,sensitive,information
Platform: UNKNOWN
Classifier: Programming Language :: Python
Classifier: Programming Language :: Python :: 3
Classifier: Programming Language :: Python :: 3.4
Classifier: Programming Language :: Python :: 3.5
Classifier: Operating System :: OS Independent
Classifier: Environment :: Console
Classifier: License :: OSI Approved :: MIT License
Classifier: Intended Audience :: End Users/Desktop
Classifier: Topic :: Utilities
